ts_rag/__init__.py
ts_rag/answer.py
ts_rag/config.py
ts_rag/findpdf.py
ts_rag/indexer.py
ts_rag/llm_config.py
ts_rag/paperindexg.py
ts_rag/pdf2md.py
ts_rag/search.py
ts_rag/tashanrag_server.py
ts_rag/visit.py
ts_rag/tashan_core/__init__.py
ts_rag/tashan_core/internal/__init__.py
ts_rag/tashan_core/internal/data_models.py
ts_rag/tashan_core/internal/decorators.py
ts_rag/tashan_core/internal/exceptions.py
ts_rag/tashan_core/internal/items.py
ts_rag/tashan_core/internal/loggers.py
ts_rag/tashan_core/internal/registry.py
ts_rag/tashan_core/internal/suppressions.py
ts_rag/tashan_core/internal/utils.py
ts_rag/tashan_core/internal/base/__init__.py
ts_rag/tashan_core/internal/base/abstract.py
ts_rag/tashan_core/internal/base/aspects.py
ts_rag/tashan_core/internal/base/attrs.py
ts_rag/tashan_core/internal/base/concepts.py
ts_rag/tashan_core/internal/base/data_models.py
ts_rag/tashan_core/internal/base/documents.py
ts_rag/tashan_core/internal/base/examples.py
ts_rag/tashan_core/internal/base/images.py
ts_rag/tashan_core/internal/base/instances.py
ts_rag/tashan_core/internal/base/items.py
ts_rag/tashan_core/internal/base/llms.py
ts_rag/tashan_core/internal/base/md_text.py
ts_rag/tashan_core/internal/base/mixins.py
ts_rag/tashan_core/internal/base/paras_and_sents.py
ts_rag/tashan_core/internal/base/pipelines.py
ts_rag/tashan_core/internal/base/serialization.py
ts_rag/tashan_core/internal/base/utils.py
ts_rag/tashan_core/internal/converters/__init__.py
ts_rag/tashan_core/internal/converters/docx/__init__.py
ts_rag/tashan_core/internal/converters/docx/base.py
ts_rag/tashan_core/internal/converters/docx/namespaces.py
ts_rag/tashan_core/internal/converters/docx/package.py
ts_rag/tashan_core/internal/converters/docx/utils.py
ts_rag/tashan_core/internal/llm_output_structs/__init__.py
ts_rag/tashan_core/internal/llm_output_structs/aspect_structs.py
ts_rag/tashan_core/internal/llm_output_structs/concept_structs.py
ts_rag/tashan_core/internal/llm_output_structs/utils.py
ts_rag-0.1.9.dist-info/METADATA
ts_rag-0.1.9.dist-info/WHEEL
ts_rag-0.1.9.dist-info/entry_points.txt
ts_rag-0.1.9.dist-info/RECORD
