Metadata-Version: 2.4
Name: ts-rag
Version: 0.1.9
Summary: 多论文 RAG 问答系统 - 基于检索增强生成的科研论文问答系统
Project-URL: Homepage, https://github.com/your-username/TashanRAG
Project-URL: Repository, https://github.com/your-username/TashanRAG.git
Project-URL: Issues, https://github.com/your-username/TashanRAG/issues
Project-URL: Documentation, https://github.com/your-username/TashanRAG/blob/main/README.md
Project-URL: Changelog, https://github.com/your-username/TashanRAG/blob/main/CHANGELOG.md
Author: TashanRAG Contributors
License: MIT
Keywords: llm,papers,question-answering,rag,research
Classifier: Development Status :: 3 - Alpha
Classifier: Intended Audience :: Science/Research
Classifier: License :: OSI Approved :: MIT License
Classifier: Programming Language :: Python :: 3
Classifier: Programming Language :: Python :: 3.11
Classifier: Programming Language :: Python :: 3.12
Classifier: Programming Language :: Python :: 3.13
Classifier: Topic :: Scientific/Engineering :: Artificial Intelligence
Requires-Python: >=3.11
Requires-Dist: aiolimiter>=1.2.0
Requires-Dist: colorlog>=6.8.2
Requires-Dist: fastapi>=0.115.0
Requires-Dist: fastjsonschema>=2.20.0
Requires-Dist: fastmcp>=2.0.0
Requires-Dist: genai-prices>=0.0.46
Requires-Dist: jinja2>=3.1.4
Requires-Dist: litellm>=1.51.0
Requires-Dist: lxml>=5.3.0
Requires-Dist: nest-asyncio>=1.6.0
Requires-Dist: nltk>=3.9.1
Requires-Dist: pillow>=10.4.0
Requires-Dist: psutil>=6.1.0
Requires-Dist: pydantic>=2.9.0
Requires-Dist: pymupdf>=1.24.10
Requires-Dist: python-dotenv>=1.0.1
Requires-Dist: python-ulid>=2.7.0
Requires-Dist: requests>=2.32.3
Requires-Dist: typing-extensions>=4.12.2
Requires-Dist: uvicorn[standard]>=0.32.0
Requires-Dist: wtpsplit-lite>=0.1.0
Provides-Extra: dev
Requires-Dist: black>=24.10.0; extra == 'dev'
Requires-Dist: mypy>=1.13.0; extra == 'dev'
Requires-Dist: pre-commit>=3.8.0; extra == 'dev'
Requires-Dist: pytest-asyncio>=0.24.0; extra == 'dev'
Requires-Dist: pytest-cov>=5.0.0; extra == 'dev'
Requires-Dist: pytest>=8.3.0; extra == 'dev'
Requires-Dist: ruff>=0.7.0; extra == 'dev'
Requires-Dist: twine>=5.1.0; extra == 'dev'
